{
  "project_info": {
    "project_number": "417713504635",
    "firebase_url": "https://omperj-3e07e.firebaseio.com",
    "project_id": "omperj-3e07e",
    "storage_bucket": "omperj-3e07e.appspot.com"
  },
  "client": [
    {
      "client_info": {
        "mobilesdk_app_id": "1:417713504635:android:8e6d68baf19d1960",
        "android_client_info": {
          "package_name": "br.com.omperj"
        }
      },
      "oauth_client": [
        {
          "client_id": "417713504635-q18jf8t4pld55sq1kuoat8h6pm2lf8l2.apps.googleusercontent.com",
          "client_type": 3
        }
      ],
      "api_key": [
        {
          "current_key": "AIzaSyAwZlkzMfIponYobgcZOZLf551p7yYKftk"
        }
      ],
      "services": {
        "analytics_service": {
          "status": 1
        },
        "appinvite_service": {
          "status": 1,
          "other_platform_oauth_client": []
        },
        "ads_service": {
          "status": 2
        }
      }
    }
  ],
  "configuration_version": "1"
}